{"cameraMode":{"drawMode":0,"name":"Shaded","section":"Shading Mode"},"sceneLighting":true,"audioPlay":false,"sceneViewState":{"showFog":true,"showMaterialUpdate":false,"showSkybox":true,"showFlares":true,"showImageEffects":true,"showParticleSystems":true},"in2DMode":false,"pivot":{"x":31.394006729125978,"y":-1.6563072204589844,"z":12.829368591308594},"rotation":{"x":0.5123705863952637,"y":0.00487110111862421,"z":-0.0028149529825896026,"w":0.8588433265686035},"size":21.17021942138672,"orthographic":false}